aiger_sat/__init__.py
aiger_sat/sat.py
aiger_sat/sat_bv.py
aiger_sat/test_sat.py
aiger_sat/test_satbv.py
py_aiger_sat-3.0.7.dist-info/LICENSE
py_aiger_sat-3.0.7.dist-info/METADATA
py_aiger_sat-3.0.7.dist-info/WHEEL
py_aiger_sat-3.0.7.dist-info/RECORD
