Metadata-Version: 2.1
Name: py-aiger-sat
Version: 3.0.7
Summary: Pythonic interface between AIGs and SAT solvers.
Home-page: https://github.com/mvcisback/py-aiger-sat
License: MIT
Author: Marcell Vazquez-Chanlatte
Author-email: mvc@linux.com
Requires-Python: >=3.10,<4.0
Classifier: License :: OSI Approved :: MIT License
Classifier: Programming Language :: Python :: 3
Classifier: Programming Language :: Python :: 3.10
Classifier: Programming Language :: Python :: 3.11
Classifier: Programming Language :: Python :: 3.12
Provides-Extra: bitvector
Requires-Dist: py-aiger (>=6.0.0,<7.0.0)
Requires-Dist: py-aiger-bv (>=4.0.0,<5.0.0) ; extra == "bitvector"
Requires-Dist: py-aiger-cnf (>=5.0.0,<6.0.0)
Requires-Dist: python-sat (==1.*)
Project-URL: Repository, https://github.com/mvcisback/py-aiger-sat
